venv_kernel/__init__.py
venv_kernel/kernel_tool.py
venv_kernel-1.0.11.dist-info/LICENSE
venv_kernel-1.0.11.dist-info/METADATA
venv_kernel-1.0.11.dist-info/WHEEL
venv_kernel-1.0.11.dist-info/entry_points.txt
venv_kernel-1.0.11.dist-info/RECORD
