Metadata-Version: 2.1
Name: venv-kernel
Version: 1.0.11
Summary: Create a custom jupyter kernel for your venv.
Home-page: https://github.com/bjoseru/venv-kernel
License: MIT
Author: Björn Rüffer
Author-email: bjoern@rueffer.info
Requires-Python: >=3.6,<4.0
Classifier: Development Status :: 3 - Alpha
Classifier: Framework :: Jupyter
Classifier: License :: OSI Approved :: MIT License
Classifier: Programming Language :: Python :: 3
Classifier: Programming Language :: Python :: 3.6
Classifier: Programming Language :: Python :: 3.7
Classifier: Programming Language :: Python :: 3.8
Classifier: Programming Language :: Python :: 3.9
Classifier: Programming Language :: Python :: 3.10
Classifier: Programming Language :: Python :: 3.11
Classifier: Programming Language :: Python :: 3.12
Classifier: Programming Language :: Python :: 3 :: Only
Requires-Dist: ipykernel (>=5.5,<7)
Requires-Dist: rich (>=10.7)
Requires-Dist: setuptools (>=67.0.0)
Requires-Dist: typer (>=0.3.2)
